falat_prompter-0.1.1.dist-info/licenses/LICENSE
prompter/__init__.py
prompter/llm_config.py
prompter/llm_config_loader.py
prompter/llm_factory.py
prompter/prompt.py
prompter/prompt_context_builder.py
prompter/prompt_template_processor.py
prompter/templates/chatbot/chatbot_persona.prompt
prompter/templates/codegen/code_generation.prompt
prompter/templates/custom/custom_formatting.prompt
prompter/templates/datatransform/data_transform.prompt
prompter/templates/fewshot/fewshot_examples.prompt
prompter/templates/instruction/basic_instruction.prompt
prompter/templates/qa/qa.prompt
prompter/templates/rag/rag.prompt
prompter/templates/role/role_based.prompt
prompter/templates/summarization/summarization.prompt
falat_prompter-0.1.1.dist-info/METADATA
falat_prompter-0.1.1.dist-info/WHEEL
falat_prompter-0.1.1.dist-info/top_level.txt
falat_prompter-0.1.1.dist-info/RECORD
