Metadata-Version: 2.4
Name: falat-prompter
Version: 0.1.1
Summary: Extensible LLM provider system
Author: falatform
License: MIT
Project-URL: Homepage, https://github.com/falatform/prompter
Project-URL: Repository, https://github.com/falatform/prompter
Requires-Python: >=3.7
License-File: LICENSE
Requires-Dist: requests
Dynamic: license-file
